partis_utils-0.1.4.data/purelib/partis/utils/async_trio/__init__.py
partis_utils-0.1.4.data/purelib/partis/utils/async_trio/async_trio.py
partis_utils-0.1.4.data/purelib/partis/utils/venv.py
partis_utils-0.1.4.data/purelib/partis/utils/mutex_file.py
partis_utils-0.1.4.data/purelib/partis/utils/property.py
partis_utils-0.1.4.data/purelib/partis/utils/file.py
partis_utils-0.1.4.data/purelib/partis/utils/__init__.py
partis_utils-0.1.4.data/purelib/partis/utils/valid.py
partis_utils-0.1.4.data/purelib/partis/utils/log.py
partis_utils-0.1.4.data/purelib/partis/utils/fmt.py
partis_utils-0.1.4.data/purelib/partis/utils/inspect.py
partis_utils-0.1.4.data/purelib/partis/utils/mem.py
partis_utils-0.1.4.data/purelib/partis/utils/sig.py
partis_utils-0.1.4.data/purelib/partis/utils/hint.py
partis_utils-0.1.4.data/purelib/partis/utils/similarity.py
partis_utils-0.1.4.data/purelib/partis/utils/special.py
partis_utils-0.1.4.data/purelib/partis/utils/lint.py
partis_utils-0.1.4.data/purelib/partis/utils/data.py
partis_utils-0.1.4.data/purelib/partis/utils/ast.py
partis_utils-0.1.4.data/purelib/partis/utils/sphinx/basic_main.py
partis_utils-0.1.4.data/purelib/partis/utils/sphinx/_templates/base.html
partis_utils-0.1.4.data/purelib/partis/utils/sphinx/__init__.py
partis_utils-0.1.4.data/purelib/partis/utils/sphinx/_static/tables.css
partis_utils-0.1.4.data/purelib/partis/utils/sphinx/_static/mathjax/3.2.2
partis_utils-0.1.4.data/purelib/partis/utils/sphinx/_static/mathjax/output/chtml/fonts/woff-v2/MathJax_Fraktur-Bold.woff
partis_utils-0.1.4.data/purelib/partis/utils/sphinx/_static/mathjax/output/chtml/fonts/woff-v2/MathJax_Size4-Regular.woff
partis_utils-0.1.4.data/purelib/partis/utils/sphinx/_static/mathjax/output/chtml/fonts/woff-v2/MathJax_Size2-Regular.woff
partis_utils-0.1.4.data/purelib/partis/utils/sphinx/_static/mathjax/output/chtml/fonts/woff-v2/MathJax_SansSerif-Italic.woff
partis_utils-0.1.4.dist-info/METADATA
partis_utils-0.1.4.dist-info/LICENSE.txt
partis_utils-0.1.4.dist-info/top_level.txt
partis_utils-0.1.4.dist-info/entry_points.txt
partis_utils-0.1.4.dist-info/WHEEL
partis_utils-0.1.4.dist-info/RECORD
