Metadata-Version: 2.1
Name: partis-utils
Version: 0.1.4
Requires-Python: >=3.6.2
Maintainer-email: "Nanohmics Inc." <software.support@nanohmics.com>
Summary: Collection of text and functional utilities
License-File: LICENSE.txt
Classifier: Operating System :: POSIX :: Linux
Classifier: Programming Language :: Python :: 3
Classifier: License :: OSI Approved :: BSD License
Classifier: Intended Audience :: Developers
Classifier: Programming Language :: Python
Classifier: Topic :: Utilities
Classifier: Operating System :: Microsoft :: Windows
Classifier: Development Status :: 4 - Beta
Provides-Extra: doc
Provides-Extra: lint
Provides-Extra: asy
Provides-Extra: theme
Provides-Extra: sphinx
Requires-Dist: typing_extensions>=4.7.0
Requires-Dist: importlib_metadata; python_version < "3.8"
Requires-Dist: rich>=12.5.1; python_version >= "3.6.3"
Requires-Dist: get-annotations>=0.1.2; python_version < "3.10"
Requires-Dist: psutil>=5.9.0
Requires-Dist: astunparse>=1.6.3; python_version < "3.9"
Requires-Dist: typed-ast~=1.5.4; python_version < "3.8"
Requires-Dist: rich==12.0.1; python_version < "3.6.3"
Requires-Dist: partis-utils[sphinx]>=0.1.4; extra == "doc"
Requires-Dist: typed-ast~=1.5.4; extra == "lint" and python_version < "3.8"
Requires-Dist: pyflakes~=2.4.0; extra == "lint"
Requires-Dist: trio==0.20.0; extra == "asy" and python_version >= "3.7"
Requires-Dist: trio==0.19.0; extra == "asy" and python_version < "3.7"
Requires-Dist: pygments~=2.14.0; extra == "theme"
Requires-Dist: sphinx-design~=0.3.0; extra == "sphinx"
Requires-Dist: sphinx_autodoc_typehints~=1.21.4; extra == "sphinx"
Requires-Dist: sphinx-subfigure~=0.2.4; extra == "sphinx"
Requires-Dist: furo~=2022.12.7; extra == "sphinx"
Requires-Dist: sphinx-copybutton~=0.5.1; extra == "sphinx"
Requires-Dist: partis-pyproj~=0.1.0; extra == "sphinx"
Requires-Dist: sphinxcontrib-bibtex~=2.5.0; extra == "sphinx"
Requires-Dist: sphinx~=5.3.0; extra == "sphinx"
Requires-Dist: sphinxcontrib-svg2pdfconverter[CairoSVG]~=1.2.2; extra == "sphinx"
Requires-Dist: sphinx-paramlinks~=0.5.4; extra == "sphinx"
Requires-Dist: pygments~=2.14.0; extra == "sphinx"
